<Properties StartupConfiguration="{E5FAA26E-FE00-5E4B-002B-F43664E326AD}|">
  <MonoDevelop.Ide.Workbench ActiveDocument="Assets/Scenes/Scripts/CollectKeys.cs">
    <Files>
      <File FileName="Assets/Scenes/Scripts/FollowScript.cs" Line="28" Column="5" />
      <File FileName="Assets/Scenes/Scripts/TimerGameOver.cs" />
      <File FileName="Assets/Scenes/Scripts/GameOverOverlay.cs" />
      <File FileName="Assets/Scenes/Scripts/DestroyObject.cs" />
      <File FileName="Assets/Scenes/Scripts/CollectKeys.cs" Line="12" Column="29" />
      <File FileName="Assets/Scenes/Scripts/ScoringSystem.cs" />
      <File FileName="Assets/Scenes/Scripts/VictorySprite.cs" />
      <File FileName="Assets/Scenes/Scripts/PointsToWin.cs" />
      <File FileName="Assets/Scenes/Scripts/HighscoreTable.cs" />
      <File FileName="Assets/Scenes/Scripts/MainMenu.cs" Line="36" Column="35" />
    </Files>
    <Pads>
      <Pad Id="ProjectPad">
        <State name="__root__">
          <Node name="Inescapable" expanded="True">
            <Node name="Assets" expanded="True">
              <Node name="SampleScenes" expanded="True">
                <Node name="Menu" expanded="True">
                  <Node name="Scripts" expanded="True" />
                </Node>
                <Node name="Scripts" expanded="True" />
              </Node>
              <Node name="Scenes" expanded="True">
                <Node name="Scripts" expanded="True">
                  <Node name="CollectKeys.cs" selected="True" />
                </Node>
              </Node>
              <Node name="Standard Assets" expanded="True">
                <Node name="Characters" expanded="True">
                  <Node name="FirstPersonCharacter" expanded="True">
                    <Node name="Scripts" expanded="True" />
                  </Node>
                </Node>
              </Node>
            </Node>
          </Node>
        </State>
      </Pad>
      <Pad Id="MonoDevelop.UnitTesting.TestPad">
        <State name="__root__">
          <Node name="Inescapable" expanded="True" selected="True" />
        </State>
      </Pad>
    </Pads>
  </MonoDevelop.Ide.Workbench>
  <MonoDevelop.Ide.DebuggingService.PinnedWatches />
  <MonoDevelop.Ide.Workspace ActiveConfiguration="Debug" />
  <MonoDevelop.Ide.ItemProperties.Assembly-CSharp PreferredExecutionTarget="a8ccb320-811e-4ed2-b8bc-c9154f1fa087" />
  <MonoDevelop.Ide.DebuggingService.Breakpoints>
    <BreakpointStore />
  </MonoDevelop.Ide.DebuggingService.Breakpoints>
  <MultiItemStartupConfigurations />
</Properties>